{
"fwlct4qkd4iutiez7fmfkonm":["18slashes","Stͭeͤfaͣn - Your Ancestors Knew Death out 10/26"],
"kjrvvgyndgraze3njddbxjsy":["1steditionkanna","Ancient Kanna `🐬​​´"],
"esxhjpdzzkylqoj5zmkwogdm":["1pekiro","Anchan"],
"frkizn3aqz4fillykrq7ssgc":["aanquinha","Anca Demeter"],
"befssizgcmq32mtfvtno6l34":["aarkamien","Ancaryn"],
"5iezevxrodbxgi3jj3rfwhrm":["aatlse","Ailes Anciennes Toulouse"],
"h3kjv7cal3nvzap2ow5snely":["afds","💀Ancient Fan Death Studios💀 "],
"cqrujfwl7o2ioldqzkt2vkby":["albayrak","Doğancan Albayrak"],
"cskpnrvlinyp4zmv2pilmv5t":["alexiosxiv","Alex (CEO of Ancients Derangement)"],
"6jprkqw4stqm7tamonofobif":["allanchorsaweigh","It's anchoring time"],
"3rywwj5lwrqncg2ps3htqcf3":["allodole","Revy | hi astarion ancunin, call me"],
"dqktpx4zfut5k3oxlk4mhsb4":["amcalag0n","Ancalagon"],
"2jkqaootdn5xywid6tfnhjim":["ancientcarelord","mike"],
"2oy5mj2wzxnggo4ekgnkqimo":["ancutahansen","Ancuta Hansen"],
"47hckmqhvu6bpnckcnz2mzxj":["anchuin","Anchuin"],
"4cdscftk3e64nrue3y6kmwln":["anchuelo","André Anchuelo"],
"6ouweyk2gmkog5kkxzqfzvbi":["anchara","Anchara 🌸"],
"7ulex6e362us2z5gc5f7b2s2":["anchimayen","Anchimayen"],
"7w5z4vfpbaky6fusul7bxn3d":["ancientevil","ANCIENT EVIL"],
"ba6wfdbscnhymx37es3a3h2b":["ancomska","Ancomska"],
"bagcaftqrj2x7ioqdb22yn3t":["ancienttoco","Toco 𓅃"],
"bfn3vck65hx7mq4vqisjeepl":["anceschistan","Luca Anceschi "],
"ckugseg52r2pj5y2hm6g457n":["ancientsaltdepo","lizzie🌽"],
"ddnp5him6b52l7e2xejh3gku":["ancommiey","Ancommie"],
"dqsqohj5mpvl2r3qpjxteary":["ancas","Anca"],
"dskzctodwpbnyl4xdm2tjcw3":["ancienteldritch","Eldritch "],
"e5yg6bl56v5lhc2lfm22rxep":["ancalime212","WonderJudge"],
"exgsrehvyam62krlfmyc2kdm":["ancientfaerie","Frigid Witch"],
"f6s2dauwfvsscfk5prsrtcky":["anchovy","Кавка"],
"gczdnw2wqtkt4czairyjtx4z":["ancient","James Brown"],
"gkca2pmdwdkgloqsyecayb2h":["anchorm4n","anchorm4n"],
"h4b6hre4zascnusedothcyvd":["ancientrelic","Ancient Relic"],
"hgjl4xpstynphaok22kn22pd":["ancel.staydown.money","ancelysia"],
"i5qsos7de4uwr3bnpdxhf36d":["anchenm","Донька маминої подруги "],
"k6owlolaisx6smx727n2mmzy":["ancientmagic","𝕬𝖓𝖈𝖎𝖊𝖓𝖙 𝕸𝖆𝖌𝖎𝖈 🐙"],
"lghbixfzbqizz4yvpljravjt":["ancientlyric","Bettina Joy de Guzman "],
"m4j7hamnyb4mk5g65eic7fa5":["ancawonka","Anca"],
"mvjzzefzfgzxkxm54vu4tmem":["ancruz","Ancruz"],
"mxt3y4nnq3jt6qewmi6pjqgj":["ancientmillennial","The Ancient Millennial "],
"n5jpnwgvrntfbtyb6qvsximo":["ancientearthling","Ash"],
"nlbqlj5wf74pxhkzxfrq3cjj":["ancarlin","An Moorman"],
"oubhul6xosaquncgzv32knyg":["ancienttome","Abigail"],
"qts3kobhfxuvtfyetp7kchwq":["ancesra","Ancesra"],
"qysg2m6g3zgtm3pbe4fffppg":["ancomdyke","Z"],
"stgjpogitxvjekx6znrx74ln":["anchorite","rhys"],
"vqgc5sngsg2k5wy3vhs55a3l":["ancab","Anca Buit"],
"w6yqgqoxrdjujv2yjjmxyzyz":["ancientsea","Ancient Maritime History"],
"wezux3f7aokl6oxtm52rs4sa":["ancrnt","J"],
"wvaybejdryz6fkmiqoasne3r":["ancientqueen","osrawa"],
"zb32dcv43hcm4gbj73loe5v6":["ancientonyx","AncientOnyx"],
"zmilyky6nj2opurri6e7isfm":["ancasarba","Anca🦆"],
"gwpm3pe7p2xigazbkjf3eu7g":["ancapalex","Alexandra Carrillo "],
"r632ds2kxsybgwx7hne3nofs":["anca","Anca B. "],
"tpb6efd7vza2qcipnpc3i6vt":["ance","Ance Zveja"],
"3fykrwp7axtmessyuhwqyupu":"ancientfuture",
"oqjjngrbdsdupscbtcjzijmk":["ancapta","jo robinette biden"],
"22ukr66fg7p3dpscaqcgv2qh":["ancestorcult","Ancestor Cult"],
"vduvlrok6ygpeeisq3xmj6dd":["ancheriom","Ancheriom"],
"xex64fxbwpgu75pcgvjtaygs":["anchoragedailynews","Anchorage Daily News"],
"ncb2wbsyjshcdywkn6xetx3q":["anchal","Anchal"],
"mkoxkaupacx7hrjc3nmuumxf":"anchu",
"zsrjb5z6xcob5dbecxdb7dfv":"anchrt",
"ocfedcb3uoyy6lrrdp5komfu":["ancaldazar","Son of Battles "],
"zgpbxd6jmcmtv2jl7ukxer6p":["ancaman4d06","Aman George (ANC 4D06)"],
"qmir7pqlzkkk2icwfiyujaxy":["ancestralpotato","Ancestral Potato"],
"ccnmpnkf6uqzfas3c3yp7q3t":["anch","안크 서마"],
"ijkvvvfajsgzmkpn3ygnafrt":["ancheol0711","Ancheol"],
"hf47fu43dfst4ucrrtli6lj7":["anchoita","Anchoita"],
"rnvsgfhp42u43xzz2tlty2ug":["ancientgoat","Fred Schreck"],
"pvxvsbybmdeukngd5ggkjxj7":["ancientspeak","Elis"],
"bgo3r6tbutr4bcslmkhekdr3":["ancienthistoryfan","Ancient History Fangirl"],
"7z6eckdakbmxbmmiaai5t3it":["ancomfrogg","Frog of Anarchist Amphibian Productions🏳️‍⚧️"],
"7a4wj5wmjmlnur2vz6lbealk":"anchorless757",
"2csafe3nhwhimn2m5ymaf2ah":["ancsantiago","ana carla santiago"],
"bgthha3fu3rqiystzsqqhlru":["anchorsarecool","Warren"],
"bay5yqdn4cd27tzf24pr3qj7":["anarchorang3","Ancom orangutan rises again harder and stronger"],
"zhwjjdg74q3t6gvkfx6lfapc":["ancoraunaltro","Andrea Barbon"],
"gqnen4fyaq3jmftqk6ow5q3v":["ancients.me","Ancients"],
"67ehkc5mae5et7utnwirpbaq":"anconl",
"y5wjm2nq64v7fjmltrk5ekda":"anchun",
"cqcx4wxk7g7oc6lud63rfbif":["ancienthydra","Hassaan Ahmed"],
"gh36bdirgt3lmzsr4k3nwjnj":["ancsnine","Anna"],
"vct4gaywaw463k2wxdoxmmqf":["anchenagoftam","Anche Nagoftam"],
"vfm2asqmta6yyf5fydumhyud":["ancientsorcery","Kim"],
"ntrcss4nbfmuovzk25nv5jtv":["anchet7","aaa"],
"wxkq4ddmkg334t7qllqwxj67":["anciin","anciin"],
"fuq63ksohx52pe56k7maehky":["annanchieta","Anna Anchieta"],
"lss4morriagmhlryl3q5ezfw":"ancestral-pigeons",
"c5btof4oi2aecb4xjexrqgui":["anchel","Anchel Labena"],
"btcvdbb3krelzm7tjmbnobtc":"anchovyoon",
"n55xafk7auhclo6jhb3ic2tb":["ancientvoid","AV ⛓️🪦"],
"43m7vi2jrplghaf35npuau2n":["ancientlitdude","Jordan Ashley Moore"],
"cmfnvixld4qkig45s2p37xxi":["anc","ANC"],
"bnrtxpwfxt2cjpbiripf35rx":["ancho","annethology 💫"],
"bok2snrvugss2qeyprzx6673":["ancla","ancla"],
"llp2m5wag5niatopjjxypcoy":["ancheicialtroni","Anche i Cialtroni"],
"vgjzmolw2ip4i2zi3tx4btbn":["ancientpragya","AncientPragya 𑁍"],
"hypjsizoh4meeohibcl7b2xn":["ancaro","Andrea"],
"cgudummqh2sjnzru3pr7n7ne":"ancestral90042",
"f2ih53hp37uzqgryfxginj4i":["ancunin","𝒈𝒓𝒂𝒗𝒆𝒚𝒂𝒓𝒅 𝒇𝒖𝒄𝒌 6⁶⁶"],
"r37lrhqtjvvoocwmhj3fm6d6":["anchiebaipor","anchieBaipor 🛸AREA52🌸 🐷🐍"],
"ofooxx32irw52u54qglancx3":["anchovyfillets","Anchovy Fillets"],
"lhrl4nqkq37i3o5wc5irwnl2":["ancientsippycup","Em"],
"723npioiohg3ozvdbatvn2ug":["ancientmews","Mews@イルミナ"],
"rumt44wijiicovytwykvejhc":["anaake","anchy | enki"],
"nzei555hh3hdzhoqlkhfhwsj":["anchorwhale","Trooper"],
"a2d7embqvydnt66x3zr4osrl":"anchorscanfly",
"qleaywnbodwpm2xcya4hhtji":"ancientfaces",
"kqynnehxgunwh2g6ofdn7ev7":["ancientwinters","Ell G"],
"fyjhuo65oesifmcy2uhrab2d":["ancoll","Alex Collins"],
"m53evmv7rh6oljkyjjo6vx5x":"anchovyes",
"iirgfi5wybf3xou6p2csw4i7":["ancientjewreview","Ancient Jew Review"],
"vb5m6f32qhmwx4q2cbbppgyn":["ancestryroads","Ancestry Roads"],
"u6ght6jf7gt6zrueuy6eazgo":"ancientinstinct",
"vcng2fnddxvv4km636y4esrx":["ancude","Angel"],
"huvtwkddbbj3hir5njrt3xl7":["ancara","ancara"],
"zafesrnb4hl7yls5oq2ep6xv":"anck",
"q5n3ljilum5exb5j42bpsp5j":["anchiew","анч (｡･･｡)"],
"hsonwx26bm6ps2mrynkg2i4c":["ancom-primate","Primate🏴🔻"],
"gid5nsu4quqwe5s4gxlaour5":["ancesra18","Ancesra🔞+"],
"hpzhmq7csjc4jgyv2yzqzt7i":["anchry","Ástráður (Ace)"],
"pf4mul4axj2bjul55vgafxuz":["ancientalientech","ancientalientech"],
"7xfqomytp66ilvtb3xpj3y57":["ancasandu","Anca Sandu"],
"tkgsnxrbrbb2np7stge5io4i":["ancillaryreview","Ancillary Review of Books"],
"ruyauz5rfjsyphdpbtg46gwb":["anceardlann","An Ceardlann"],
"7upbcnde3baenfgxzxwytrnq":"anchorman",
"pzd6sxteaq2gkchmxylmmu7o":"ancientmystic",
"gyqzksn3xn7saro44amxs7xn":["ancientbaldguy","Andy Mickelson"],
"zb3xigxcpqfm6egsityz7pit":["ancaleth","Roxanne Phillips "],
"k32y3t2esxw45qz52n4nauln":["ancienthistgeek","AncientHistGeek"],
"juqjyrkhlxnsqorbsix3x57l":["ancomscicomm","AnCom Ⓐ☭ SciComm🔬📣"],
"nb64iz4hcmjggiuoek5pig4c":["ancoro","ancoro"],
"xhpmhg53rc7ghjuwlumo3bpc":["ancient-tokens","Clare Rowan"],
"whl6vdc2alfbnvw75lix2ql7":["ancientpixel","Ancient Pixel"],
"tbf53qsb24if7k5owp7vhxjd":["anchnzzrn","касіопеся"],
"mqyag2lvusg5s6xidgyy7p3h":["anchovis","anchovis"],
"hnisc35njz5bpaehoalpkhrx":["ancientflounder","AncientFlounder"],
"ryd6r4zn5wy5dualn4mqj2a5":["ancillary","🤷🏻‍♂️"],
"ic5zmqjsxkbduqzuueloynil":["ancestorregime","Carrie Carter"],
"4ciiiybm77ipwqjvsey4icfc":["anchous","dekilka"],
"kc3dg7wfd4yiccosea6gwkcq":["anchorbabynotes","Notes From An Anchor Baby"],
"5sseqb26le3ufcjd5ii7krd3":["ancientheir","king in the north"],
"5xf2rfwgws23umqlepmtzmpj":["ancc0","앵걸"],
"5h4ts472bc2tbib253rcx3bh":"anche",
"cnibjl4punttpmhx6wy7jlya":["ancient-traxk","Ancient Track"],
"jgozkxri3j3reqcapc7esb2s":"anchises",
"mcll4ynvtko3vh5ccxh2ib7i":"ancym",
"kzfcjmz2puiuz6pjzrg76g2t":["anchjones","Andrea Jones"],
"2zirzzvkszld34a4g7e662ek":"anchoui",
"s2zwsv2kpybgzpmk5mkhknba":"ancientgreekci",
"hbocrgj6o76zqjgsupqrmr72":"anchoritegames",
"aot5htnclskfk6mbkfuh67f7":["ancestryhour","#AncestryHour"],
"dxprd3zn2g62gj56fpjq5r4v":["ancelineonline","Anceline "],
"4wzobej3fa42njv6dnetipu6":["ancill","Ivan Arsenev "],
"ovsj7enxvy5sfqgubjpbqcvb":["anchan","anchan"],
"pxxkl2apk4j32lmv64pwu4dc":"ancrath9",
"wvp7k2n4htj3l7r27i2utjle":["anccerys","Cerys"],
"lb3zkqki3qyvzgquktkvm24v":["anchoredshores","ozzy 🌻"],
"l3q2u3ixt3pg5p4hlvhvx4l4":["ancera","Ancera"],
"x2s23ajksdbbmsg4r2wybvhx":"anchorcake",
"iwut2tc2njewzkra4ayvawcx":"anchobii",
"pi3y656gbzn3ko2g6tl7gna4":["ancientcryptid","Cryptid’s Puffy Pucker"],
"iewgocitamrtt2jevfzicasd":["ancientmariner","Nemo"],
"tg7juj2mqtpgywmvctxvloak":"ancientmagician",
"mnbpkklgnac4vwgeocm7p6sq":"ancientannoyance",
"7siwektwdhpnffzff43pcqjy":"ancientsites",
"4up3msbdjiz2chw2whihdma5":["anchor-ice","anchor ice"],
"ayvhw6nl7oimjt5pvd6kaju5":["ancientunicorn","Terri the Ancient Unicorn"],
"eobmi74ul6scxfbtikx6bfee":"ancientpersia",
"oyz6rbivha3ycra5rfbgsefx":"ancientiran",
"sk3vb5wqvgx7eeqtomqy62nk":"anchantedone",
"4ihlsa5p4ho5ywm3abusj46c":["ancientalienfox","Hallow Star"],
"sjtsyip6lsmh5ykjrnuwjali":["anchovita","anchovita 📎"],
"4pvjsfcbp6e2fx3q523ae7cm":"ancap",
"a4qan4hawrbh3fjxtgsodauz":["anciluart","Angel"],
"c3s6e34r4t6ubjpyucwhuskd":["ancelwolf","~ AncelWolf ~ "],
"irsghnsthwmfu7bmscgntcw5":["anchi","ANCHi"],
"wh66hpokml44alwmx5abyj2j":["ancines","Daniel Ancines"],
"mvvmitnffqc7hliph6qtsqtg":"ancientanubis",
"yxfx2s2yvmpfbiozfknfnavf":["ancaguehlstorf","Bazinga"],
"kvcw2t43yfrhs7l7ynbsbk5u":"ancgreek",
"n3wzgeiebhicwqzrzyqxhnlq":"anchinya",
"ugvle3qli47aml7fy3tmha4w":["anchordawg","Anchørdawg"],
"4xg23sajh2ysymhj5xxa4na5":["ancinidae","hal"],
"4tkgzaylyo6xo7ffddq64n4x":["anco","ikamoc"],
"ic7acuwqrb4wwyxezbpxgleh":["anclet","Anclet"],
"5sd2vaat2hpoycvdry6p6abi":["ancientplay","Dunstan Lowe"],
"aami5llsqmai4yyqb4lxdycc":["ancienthistory","Ancient History"],
"sowx2dfbkvzg7mxg2vq66c4o":"anceldelambert",
"ereoh6lojwz4iqxg7bzaygta":["anco-writes","AnCo Calcen"],
"ji3p7iht7vb7sjs7j5knagpv":["ances","Ances"],
"vmbltkxms7qr52mpkrvs3be2":"ancomhenry",
"oxdwyke4gymru33ebxbzcw5k":["anchansarr","힘내라단팥빵"],
"dcfngermvwhfu2j23pu4o4yj":["anc7xr","닻"],
"u6ly2ev62b5r67ze7exhq3g7":["anci","Anci"],
"cqnlw2yfq3gmv576m4fnns7e":["ancariis","Sun"],
"gmuidqnnuuvmp4quapkvklm5":"ancurlija",
"lcfquwsvufjskksywtftj4bh":"ancientark",
"q3ashaytjqffmph35fg7jz2t":["anchorsamourx3","Jenny"],
"iphnnl5xv6v4jfpj3fxj4jz2":"ancelas",
"xrq77rt6s3tbym3el5b6irei":["ancientwings","ancientwings"],
"wkpn6y3umz6oy65yiylmtza6":"ancalagor",
"u7xywytpfgbwtxat7vx2kofn":["anchacha","anchacha "],
"dmotgxaxlfza5zvnu5o2l3hv":["ancavdky","Anca masked "],
"qi3lp5ietpksslxleahz73ey":["ancatapardea","Anca "],
"jiraxwyqc25ut5wlak5cw4yw":"ancientindomed",
"nyjim4qex2iwlrpm6gmil2he":"anchors",
"7l2hdfctyvnzvmxpvewp4mw3":"ancientmonkey",
"b5a3yf4wwxiy5vayrskdqhke":["ancoar","Ángel Corral Arias"],
"aelvsg5uuq5nngif7yoq4lc4":["ancrann","An Crann aka Roger aka Rogueldr"],
"uwnqrcgo77k5qmv5pafstzih":["anchalk","Anchal Khandelwal "],
"pufsgw6g6oukn2la2auzmmyi":["ancom","mamba 𓆙"],
"pcechmf4rnyxdw6i22fggtfu":["anchrannog","An Chrannóg"],
"whphqkvt5irehtrxvkq7pdfv":["anchoram","Carolus"],
"3uslzmzdgssuh4b5sjoszvtx":["ancurio","Sturmlilie"],
"ilqvxmxgzlzap2j5yktroozj":["annunakitty","Ancient Alien Cat"],
"ifsm4twl4ehythxcvadh7ydd":["ancatis","ancatis"],
"nc26qkfdxwxhxeylhojnir62":"ancrath15",
"37oldbc2slcdzkta3zhlsuzl":["ancula","AnaBanana"],
"nh52dcizy3d4x3gmfw67ur3c":["ancientpearl","L"],
"akocgslikj7ajq4svystlsst":["anchisss","Sayaka Sugie Shimada"],
"czhgt7muv3dwdbsmoiuhbazp":["ancillarybreq","gethin"],
"jgw2wk6562afctrtfbntssmv":"anch0r",
"55hxdhzesqzqutumj5s7tssk":["ancientgrapefruit","toranja antiga 𓅇"],
"lwkrkhfuwdyn4rvl3tqkrdfh":["ancientlotus","れん🪷にね"],
"qy4m3riswcpuwngatkvc3urc":"ancreamfa",
"d3rxqem47awnfgjdx3xb56wb":["ancianamother","La Madre Añosa"],
"6ebnndnzsxkaihpwfubmm4ic":"ancleiteanach",
"bte6vy7ixy45wbsi67e3iisb":["ancalangon","Ancalangon"],
"g5zks7dgymlapw5aeav6dm26":["ancalima","😷Ancalima 🏴󠁧󠁢󠁳󠁣󠁴󠁿 🦄📯"],
"fb567izk2pm22cz74sgy7gld":["ancientcraftuk","Dr. James Dilley"],
"75pxp6stw6mnygu2si6haqjn":["anchorroot","Anchor Root"],
"35pzw7lyk5trza4l4c3wojog":["anchen","anchen"],
"6jsavqzlmmev3f52ktjphoyp":["ancantu","alyssa cantú"],
"zzbldwff5fq4ayb4aikcntqa":"ancr",
"pixgimpdst22ygipsrxs2k5u":["anchvie","AnChVIE"],
"ps3igl3rjvqknprvjxqnhuee":"ancalagon",
"ky7vnsmogxhtb3daxugbbzih":["anchovymouse","Anchovy "],
"76kviwt3h2a6affachnjjen6":["ancoapple","阿湖"],
"t2wzh5l2ecluw32tg5fyrvnd":"ancatamaideach",
"jslndessegn2gbg7tzixluyu":["ancientchaos","Ancient Chaos"],
"44ox3jpy5rlchmyama4up7jq":["annetropmarrie"," Ancienne sujette du Royaume de la Choyance"],
"7ptdiwm7dsxxnfrlnkf45xur":"ancient-millennial",
"4z43rutuqlze2o7j2bhxy5pa":["ancientremains","Koiseki"],
"klkwlcuzp2otkakuc5n4gf7p":["ancientfairydcg","Rythm and Balance"],
"kgh54y66evx5fwtpfclhvcc3":["ancientpuzzles","Ancient Puzzles"],
"m6ip3ym3xvhfpzjiynfezvwv":["anr48s","Anchor-N-Rose 48s"],
"qkvor5zpxkwatf56p2egrlxo":["ancom21c","Ancom"],
"ve55oivopt5vomltkkkswjw2":["ancorvb","Ancorvb"],
"7uo5qk7owy6aj4d3hh3pamlk":["anchoredboi","An anchored down boi also known as SPaddy!"],
"wqmfcnwzpsopc4qh7g3apyyx":["anca-spatariu","Anca Spatariu"],
"n2q7gfcw73oi2fegdd647cb2":"ancestorfiles",
"i3taempjw776dg2ajz3oxlr4":["anchorstine","Justine"],
"lzmhhtpokiptgsv7xsbvid43":"ancagarcia",
"3ryncmp355voqfnsvvpywdu2":["ancientmew","Ancient Mew"],
"vwgibdcmf4b4tl5oehr46mvu":["ancasfaerlea","Dr Anca Sfärlea "],
"mxzulb4blep7xo3fmy5e73o4":["ancolibre","LAncoLibre"],
"bpyy2kh7l3pbuovwfirqhavl":["ancpru","Andreas Prucha"],
"skedw2i2ee2asm5gbcc6txon":"ancientaccsyt",
"wf3p3y4oue2ubivdwzjgnivc":["ancronzz","AnCronzz"],
"4gskxrcb7hyo26yo3qc6ur7b":"ancate",
"dvj6p2kxgc47wtf2yqhilbfs":["ancientsaek","Saek"],
"ub6m5qnkgtuidnevmeyzk5hk":"ancienttitanide",
"pcji6uhfthpxyfqi5l56wg5h":["anchovytime","David Díaz (Detective Papaya)"],
"2h2uuwxm7qouociliyfteuyn":["ancientmagnolia","mica 🐸"],
"sqe3ebink5ikyq6en2m7v47w":["anchorred","ANCHOR RED"],
"fvp5xthbzpohdxffypn6zxzj":["ancientanmodern","R"],
"qtmutei3moidhkrfodhtg4yy":["ancientrudecicada","Japhet (Yah-fet) - Secretary of Absolute Goldlewis"],
"u22tgexifbpqsib2ewc2544h":"anchilee",
"uszee2bsogvpujbq76pwfxhm":["ancetetere","Ance Tetere"],
"turr2kefqdga67x6lar4j6es":["anchorhowl","porto 🪷 kasen brainworms winning"],
"fo23cfzjvbgoebqv4jploiyi":["ancientgator","Gator the Anarchist 🕷🐊"],
"vazjgrmn3i62rtrgligedd3a":"ancomrecon",
"w2mjxijdf573ohztwbutxsa5":["ancientoaks","kuma"],
"xt5o3jsxm6ua6fpplpbg5van":"anceia",
"xwpq3l7cuo4yfnvociwf3hop":"anche61",
"c6ynfl3vtbkmvo2x5u2sdcrg":"ancientalien",
"4w4lfmotrbpcm7n2s5o7fdca":"anchousdraws",
"fu7uziy3nufwnlrcaxiuaega":["ancomaj","Anccccccc"],
"kaye3wj2fd3eujzoiwd3rbff":"ancao",
"nrlwhsuuapyvsy634hey3ir5":["anchoredmama","Ariel"],
"joaf3u5s75x5hz3grjwabvms":"ancout",
"moysjflvizfrhgwwm6ht62d4":["ancaegis","Aegis"],
"2z54jlklwhri5x5vlru3dz66":"anchoyade",
"qjexfowxhlyknldtrymfbcw4":["ancorealm","Ancora Jay | Librarian vtuber"],
"z4v6eijcduzaomnk6w43rc3q":["anciel","Stevan"],
"nbe2qvugdhooftjbnnr47zmj":"ancodia10",
"iii37ioovrnc2hok7blxkin4":["anchiya","ANCH"],
"73tsjrnhw2eajywu4ilolk3w":["anclairqui","Claire Anchordoqui "],
"k7yb3g6ypjshsqohtu4463xf":["anchieri","Lucas Anchieri"],
"fxrxmdbvzea5m6xnq6giflsq":["ancapsass","Ancap"],
"77uy273i5zadwwmtgrtdsu22":["anchovie","anchovie"],
"mjq45o764soq5ynkxxmwatdh":["ancounabe2","家電あん"],
"52omptmp7ghhrsrirch5cewb":["anchoa","Anchoa 🐟"],
"6tlypm3thvw5ye3r2xwejcnt":"anchor71",
"g5kttji7532wsy3ows442ean":["anciskold","Anci Sköld"],
"ibunanqwjv56z5r62nuubume":["anchoredsails","Mei"],
"i5j37qj7akjkvhgrsfbigzbx":"ancharoo",
"ebxlw2uvuiftq7jwhs6unmmm":"anchistorian",
"kmytl6uodetem2fkhtbokqk4":["anchoragedeadbeat","Anchorage Deadbeat"],
"ebrxwrmjsasudz2njjdvzfaw":"ancientfawn",
"2w5hi6ejb6dg2xpzyemffndb":["anchipixel","An Chi"],
"agmpktacu3bb4vkeyjc2ng7r":"ancien23",
"alwqlzdkcfz7u6zgv3unbqgk":["anchor89","Mark (Anchor89)"],
"h6rqhg2ufyjf4offyszmte4b":["ancoly","Ancoly"],
"wbdo6bgnj7wuzcuckl3me5mu":"ancestralavian",
"uixdait4ffroh7crc3susbss":["ancarion","AnCaRioN"],
"64qmzqnygbjqtsyfottel7o7":["ankr","anchorman"],
"cjhzs2qcmv4qttstjnd7ntzr":["ancretpoudre","Ancre et poudre "],
"k57f6dkpttiaybrjnwxa2bmk":"ancasterguy",
"wluk4axc3vrhnnpzdnjrgdpy":["ancelstephane1","Natsu Dragneel"],
"ujqbfhuageaulr56x4tlgnum":["ancientbrute","Jen Kinson"],
"7g3ot2onxhscx256x2vgb65c":"ancientjacen",
"cjo7lqc76plsih5ohshsdytx":"anchee",
"42sa7n64vzjxo4ny5s3sathw":["annoqed","Anchor"],
"kas5bpdb5njaggfmvtvd62do":"anchubisama",
"mjf35lz4axm4m2sncep6goaz":["anchayuri","✧*Yuri ✧ ユリ*✧ ✨VGEN COMMS OPEN!"],
"nrknartlibiiisd54rr36moa":["ancelin","Andrea"],
"rzosb2rh7etz5vy6oyqdme6z":"ancy",
"yz5yehg6c5xw7oixytuqycss":"ancr49",
"q4oj7sw577qhvr63mm4j4znf":["ancientform13","Btc1mil.Eth "],
"x5z626n7gqhytj6rax6336f2":["aoh","Ancient Order of Hibernians"],
"bvo7u5xlo36ileg356zsc2uu":["apsciencebydan","An'tdroid's Aperture Séance 💛🤍💜🖤🎃🕷️"],
"jz4fl2ssdogt2ht2x5vux52c":["archykirin","Frederick the Ancient"],
"azkqdus4wvjr4tm3eq4m3wqz":["astarionancunin","Astarion Ancunín"],
"lyanbwrpllr3twhnc2k42663":["asth","Anco Scholte ter Horst"],
"l43j674se5n2t3a627kacmzr":["axellae","Ancillary Beef"],
"clysrte5hyzpqj6nrpqsj3zs":["axiomofequality","Ancsa"],
"6h5dj7qzlpw5obvx4lvgnpka":["b1anca","♡ Bianca ♡"],
"o33daceq6a7eqg3prhtq24ua":["badancient","Bad Ancient"],
"gvzr5nhew3rcxxpkjqadun67":["bea-broderies","Béatrice - Broderies Ancestrales"],
"h5ak622fxcawoxk2zfs6cnbo":["bibliotecaances","Biblioteca das Ancestrais"],
"uhrx3h74ublkt6pskj3uc2hw":["biglebow","Anchit"],
"466dxbogbm76uzlnwg3gueyv":["bigpapaburgandy","Andy Anchorman"],
"pnfhw4grk2awjv6bq2ihyqq2":["bloomeralles","L’Ancien Vagine"],
"4ox7eano4lzeuqdusf24dobb":["blecher","Wisdom of Ancient Greece"],
"pgabi4bvz7pqstmbrfroahwq":["bluedoganchorite","BlueDogAnchorite"],
"wpmvdsmtlvgitxbekmhw6h3x":["blueancora","Blue Ancora"],
"mb6ufwdrv5ogytazluarelqa":["booksomewench","Bury me in the ocean with my ancestors 💖💜💙"],
"d5cld67yewl5is7i7pzqrcla":["boneheadsanon","Anch"],
"cnvtqt36sowividyb25y6j4b":["bordersancestry","Borders Ancestry"],
"zans5h3ukbgcgdghlpx5iy3n":["caitlinsnark","Ancient Queer Bickerings"],
"inmbom34ckf2tqaqvndfubhu":["carlg","Ancient Lights"],
"crjadfrsht75dshdtvw7pgp7":"carl4anchorage",
"to3mtlaa7mtwcepddgbyn5af":["caillouancetre","Caillou Ancêtre"],
"ivhj2fpn4gsglpe7hiohbwgo":["ceewxnder","ancee (◕‿◕✿)"],
"4s5ardkb3a6qcsrbhucl6jw2":["dacretu","D. Anca Cretu"],
"uacctp3vxyrgkdhqn37hlyvp":["danancona","Dan Ancona"],
"6yfxhzgn5gjxbzfawsyjanmi":["danclaude","It's D'anclaude "],
"piosh4egfe573ws5enl7avst":["daylightgen","Daylight Genealogy • Shining Light on Your Ancestors"],
"fyda4kybqauxpb5gawefmpk6":["delanchor","DelAnchor ⚓"],
"i5obz3pxu2qejtlpue2pwltd":["de4thbeds","The Séance 00.04"],
"vgrrosiy25yqmtxf3kzwt633":["deckofancestors","Deck of Ancestors (Sean Vanderfluit)"],
"ghanf34op55r5rmslegjrm4u":["dmeance","Didier Méance 🔌🔋🚙"],
"p4gtnkbzcvt2rgjjuhtncovk":["dogancan.dev","Doğancan Mavideniz"],
"wxf3at3nn3akbpe6v53umoyl":["dogancanozturk.com","Doğancan Öztürk"],
"ij5tas7ytsusixryrvqqejix":["dogancan","Doğancan Urul"],
"djye5jyajlqoxatkqyvrzid6":["dunestars","Ancient Eventuality "],
"4dby6usj76azc3gbmdeqfra7":["edamanchorman","Edam Anchorman"],
"btsoc2uch2azmhkvhrujakbn":["elderofancients","Elder Of Ancients"],
"5dubgn5ymhn3iyvuasm2766i":["estepepin","Pepe Ancosmede"],
"2v6r4jjwdi66svtmclbcsalh":["firtyfashion","Jenn Ancelin"],
"uycaiu5ogl75fdduod4uuxpw":["fidelcastor","Le twittos anciennement connu sous le nom FidelCastor"],
"y7ux4zvdi5f54dokizjs5q4x":["flippinglipping","Jack \"Lips\" Anchovy"],
"mmzxbdf2n5ggxgfzt4ne4pu2":["forestonthebeach","the shadow of forgotten trans ancestors"],
"k3yxjqojjqmrpchgmdiovgvd":["freyadezna","AnchoBit[e]✨🐟"],
"qrbe2blyn5h7onl2tt3ereqq":["geneamoi","Chasseur d'Ancêtres"],
"tdbrqoap65gr4633dkr4tnxr":["greatancientone","@GreatAncientone "],
"7hri6ibbmswgskyteg5kwkfj":["guillaumeancel","Guillaume ANCEL"],
"xddfgqmhozxkevcsm3ttza4v":["historianca","Anca Wilkening "],
"pk4dle4hq4z2bnx4cyxdzjxn":["holyanch","ANCH"],
"vlrztkjlafjjqqvxn7zkk26b":["hpreparazione","Kittysencula anche qua"],
"ohib3xaxo4jc7vfkmm7dobqv":["hunterparah","Ancient Hunter Parah"],
"6qil7i4wwzti7ru23b273vlr":["ikanbillys","May (murderous anchovy) "],
"dlix3ik66ajcv7xdjnmew53l":["iran-bastan","Ancient Iran"],
"yunrkdwn7hr6xbns6nhbqmbh":["ivnu","Anciã Esotérica do apto 71"],
"h7zl2swpsqn2wfmgzzgxba5y":["jactdurham","JACT Durham Ancient Greek & Latin Summer School "],
"qceg33mfaje6smu4nketo2u4":["joojooflop","🐝 anca"],
"2v3n2tasb2udrsktonmqarj4":["jordanancel","Jordan Ancel"],
"pad44cqxrrzcy43vpr4vqlvz":["jollyanchorking","JollyAnchorKing"],
"4mp27jhblkgscnf2nwpewlfv":["joseanchel87","José Anchel "],
"vhrpcf2x6paxvt3shyduefrw":["kharakillalla","KatKilllalla,except fandom.  I am 40+ and ancient."],
"jmu43yff5ohpkporiaojy426":["kitaensilva","Kitaen Silva 🍁⛩️ Ancient Nogitsune VTuber"],
"daeafax6jj7iokurpxrun5aw":["kk03killer","Anchor🦁🔞"],
"yvqbqvlwjxlk7xs5ta6k4pe3":["koraa14","Ancient Hyperkoraanian "],
"kajnkqz5pct65mczhurkcauh":["ky-ancom","KY ⒶN☭OM the Himbo Carelord"],
"qsmrmopa4p2vpwg5dundvdmz":["lauraancona","Laura Ancona"],
"4m3zcnamcnkhcdmeafye7ee3":["leftanchor","Left Anchor"],
"xoaz5yc3bylfttgy5vn4sass":["lostingarden","b!anca"],
"rcmdiuszsd2et6t6jfsdstjq":["maryzoso","Anchoress"],
"vnfyankastb7jgaq27rss7qp":["malcolmsheppard","Huge Ancient Red Worker"],
"ip7ea2a7qs5imhuvcsjndmw2":["magicspreken","KristaLyn | Modern School of Ancient Wisdom"],
"aoqqfhvcbmlccewki2amoyxa":["magicaledford","Ancade"],
"bwgm7yhrvzfqqddajvgf5w3d":["machicomaki","anco"],
"nakiuay4jfru6otsi755pppy":["mastie","Murmures d'ancêtres "],
"7aqd35hr7upl4puhyroeyknr":["madamebutterfly","La Ancestral"],
"jv3wxf5jrwzpu4vp7iqompqu":["megalithic","The Megalithic Portal Ancient Sites & Stones"],
"u57xtenfnompo2chdhi2idj2":["melancholie","Mel Ancholie"],
"pcr3aeckxjhqrg3cveup3m7d":["mel-ancholy","Mel"],
"ji3qsk7r24mrjzhfhvlwytue":["memeank","Anchang🍡"],
"zvh6ufheu6mwvbdh57xfuh4c":["mithras","Mithras - Left Justified and Ancient"],
"6p3kgacu7jrqji46de2pd6bw":["midwestancom","MidwestAncom"],
"5x3ogpkxzdtamcbl3ij5cxlr":["monicat","Monica Anchelergues "],
"5usesy2wlpd4pezay6mfrh5c":["mrsmarfelous","Ance"],
"avwocpj7ypw3rasdd7to3jtf":["mranch","MrAnch"],
"kexwfk2x4dtluk2ssx3j5tb6":["msanchovy","Dave Anchovy"],
"37tznnbuv6lcb5nslzg2wyjs":["n00ance","Kratom Daniels"],
"m5pkqb4i7rujtrqszrloxsgv":["nafc-anca","NAFC - ANCA"],
"rsmersqx5kta2ika76dbkjmd":["ninitrava","Anca"],
"j7pxz7524c6s357wlonnyzhx":["nigeltheancient","Nigel The Ancient"],
"4akvfigr2aa4p5vgp3m4vihm":["nismofur","Nismo D(ancing)AD"],
"mufjncceeeoxejd674wfprsg":["nicolasancion","Nicolas Ancion"],
"5sgr7u7mq3ochbza6aybttg3":["nooskadraws","🌿alex dingley🌿 @ ancestree"],
"jz73io5ubgae7bdct2unl2zt":["nsymmes","Ancient Woman"],
"cmmd3mmbhau3nzyh5ub5aulp":["padreanchoa","Padre Anchoa"],
"tf7gtiokjeqqkacocjilv5yl":["paranoidanchovy","Paranoid Anchovy"],
"243znbjtuqinyebswl7xwhma":["palomab1anca","pal🏹"],
"vdgzds4bkle275k64itdfqad":["padreanchoa","Padre Anchoa"],
"w2vftbw2lqfjj3wdn3x4xhra":["peterclines","Peter \"Ancient Horror\" Clines"],
"ybkhta4pszf5dqfw6hust6it":["petitdeux","Petit anchois mariné"],
"am5ah6nj3yctpzoeggpyfbfu":["philoglossa","Pre-Hellenic Loanwords in Ancient Greek"],
"pkmwuklbetfgkkftw2ffiqyk":["priscyll","Priscyll Anctil Avoine"],
"fivgsq527bu66asm7oty7izc":["rainerfalls","Rainerfalls [Ancient Fae Storyteller]"],
"l3rvzxwi24axafcjdwyipnlk":["resaustrales","Res_Australes: Ancient World Studies, Australasia"],
"jxshgkxhgvaxqmkwylcck2uq":["romansito","TRO Anc"],
"ttg2yzpbzuedme4a66lvrswz":["saintchristopher","a ancient man"],
"eialbwfm66nwnvzvzdx52b6r":["saveancientstudies","Save Ancient Studies Alliance"],
"culkfvdnebfe6xztki5lg5nu":["scd","Séance Dungeon"],
"v66lo42pbnhfuptab4hr7hi2":["sethpartnow","Anchorage Man"],
"v6m37t4lgj3k64xkf3peu5n4":["shadecrux","The Ancient Critter of the Dark Forest"],
"bmofsjn2ebmjrdbp2j6m5iwh":["siranci","Anci!"],
"lwigqcovzgjme6pm2wngqtoy":["spindriftdancer","Ancientharp"],
"w7gjsdlaalr4ouvubxwz7x47":["stevie-ancasta","Stevie"],
"rih4qrhjmva53zpza7wjatlo":["stargazerlil","🌈 Lil 🏐, Ancient Being of Fandom"],
"uimzilk22u2t6vjvbt53v4jv":["streamplace","Stream'Place 🎬 - (anciennement PNO)"],
"ntpraawsdoa3jiygkajaaejv":["sunaix","Xavier ANCELIN"],
"bn5kokocbchvropsnmcsoubg":["suiren-ancr","Suiren / Ancr,"],
"lbj46p3yu43cex26xpad7l4a":["szaszsam","Tome of the Ancient Incognito"],
"uvldr7gn2tkste4uia6sm6zl":["techiedawoof","Techie da ancestor doggo"],
"rnnp4xgmn5ptcr4wiegqqukk":["theancientone","The Ancient One"],
"j2s63bvrj6q73vuoaxpu55ri":["thirstygecko","Kevin Anchukaitis"],
"qatsw4uqyrg6vobm7mzfwwo3":["thataesthete","Ancci"],
"kixksssijqm2wrezlq67d5ak":["thelastwolfard","Forsaketh - Ancestria The VN"],
"c2ug7zp2bjil7kqldxe63yjn":["tsuge","anchor。"],
"7jvxwbkxkzj3a7otgqahvb55":"tsubu-anco",
"tjrxleowqoz7dy4yj4svohyj":["urbi","Urbi Anco und die Catenaccio Boys"],
"fkd5gr4h63bsq26eo26sjbrr":["variousartist","Anchovy’s Fuhrer"],
"72f4f4t2ugkaylfs6ggxwzem":["volfranium","Ancient coins"],
"4hlm26r4jvw4ej6xzj6hhi5j":["voidcharms","≪astarion ancunín's big naturals≫"],
"xymlbdoiwsfuychml2sgnpzz":["vulpesancilla","Vulpes Ancilla"],
"todci7bayo66ec2x65edcruh":["wallacyanchieta","Wallacy Anchieta"],
"acdf2r6ua7t6qmf4kjhuy7vd":["xandari","Xandari | Nuisance of the Ancients"],
"2j5wc3eq7kdj3aucurxstapd":["xlranchor","Anchor"],
"li6i747qi25ngfz5x4zeujwj":["yeti6ancient","JustAnotherStaffPuke"],
"upy6ahi2qixrf3rfmeij6bbt":"ancieque",
"dzyxmr4n4kxjvnrc3rcsfmos":["ancientorso","daniel"]
}
