{
"glpgvgps6m6sfkcsu7b6rz6a":["aab465","Aung Aung"],
"lxbvxlwrjlis3pk57wqgd2na":["aaunala","Aki Aunala 🇫🇮🇪🇺🇺🇦"],
"uych7krl4ssmbzhkanauqcdt":["abortion.company","Auntie Phở"],
"7ly37ssgaei7hxvpa7iwqqqz":["academicaunties","Academic Aunties"],
"ity65ehqaptramva47zsefzp":["akmoe","Aung Kyaw Moe "],
"z2hth6ja3puswld2s7diyxyj":["allroadshome","Cubone's Cool Aunt Who Takes Them For Ice Cream"],
"dwnfr4ltded7m7kdpu2zxqkt":["amesie","auntie ames"],
"ubgslkeiey3avj3cwrha3j3u":["antigonized","aunt dad"],
"pscuusqns5474te3teh5bbb7":["antigravity","Or, Auntie Gravity, if you like."],
"uuw6quc2ga4ego4lkyzk5omz":["antauntgaming","AntAunt Gaming"],
"4usrtm4625uucffo4pbtez5q":["arit.dev","Queen Arit 👸🏿#SpicyTechAunty 🔥"],
"4fsuw4bzk4j5va7nlc7kbfu6":["astarkvedja","Åsta Mari Aune"],
"23zwa5kwhh3dqtzvp3a7dv4l":["auntiemar","Марь та що тьотя"],
"2umzdqto3j75ssii6kf4jbly":["aundre","dre"],
"2wfq23pfnq5xdwtdjahouutm":["auntymoira","AuntyMoira"],
"6dkpcl2vvshl74tnyhkblnt2":["auntymaimai","Auntymaimai"],
"6uxjgy4btkho76lcwiowdqbr":["auntieentropy","Elizabeth 🌘"],
"6zfhi5qxzoyhxocecc4liyxk":["auntyem","Headly Westerfield"],
"7k3qdp2nkibhspwrjz7hkpgn":["auntieoddfur","Auntie Oddfur"],
"7yjy6n7hjoouu3idnx4zjzgm":["aunpalmquist","Aun Palmquist"],
"aufexpeix2g2sujeveb7umhz":["auntchalupa","Aunt Chalupa"],
"bh66u4f7qfxxz2c7r7b5oxz7":["aundawyn","Erika Aundawyn"],
"dq7dgzckqglcew6edmrkfx7t":["auntiesocial","Auntie Social "],
"fsm3gvwkhataq7u6el7tzflr":["auntycarrie","Carrie"],
"ggnqwr7v7qorq7spiq6ah75f":["auntiewolfie","lucille ballislife ⛹🏼‍♀️"],
"hfrsymmxsjinmykrob6onp3h":["auntiejafo","Auntie Jafo"],
"htbd7csb35m6ovi2l3q4e3mo":["auntieaintnoway23","Auntie ANW"],
"ifopa2vapcwxzbzq4x7awcyh":["auntiechrist","The Auntie Christ"],
"jappw5z35r3l5whhpr2cyw6g":["auntfritz","Aunt Fritz"],
"kf4o7kcpdp7uey4jydodtbpi":["auntyfeeble","Whaea Fi"],
"md2i6gdzixub4bwqjbycapox":["aunhana","𝔥𝔞𝔫𝔞 🪷"],
"mic4bzjmj7t2cik6vjp4iuw5":["aunthortense","Aunt Hortense (acquitted)"],
"mnws3vyu3br3rw2uttaaoswn":["auntiejoan","Auntie Joan"],
"mz5w7wzshl7igpbhtsk5cl2p":["auntiekels","Kel"],
"n5epqyr476ldiu5aywhtnjul":["aunticles","Kate Marsh 👻 haunticles"],
"oncij4s2rqf6ziyqhiee7ams":["aunfire","Aun.Fire"],
"pdh4zmxcmzsmnf4w62mr3krj":["auntcindy","Aunt Cindy"],
"q6cwe3cetgazwlqatqlizcro":["auntiecheesus","Auntie Cheesus"],
"qdygvbuhqggyjr25svar6xeq":["auntrob","Tusk Fangtooth, DDS"],
"qiafa4evdfu5xxbmj5opds5p":["auntiesis","gus"],
"sia4f7qyjbcjl44o74aialib":["auntimusprimema","Auntimus Prime MA."],
"t2r7mrmc6hz7tz4zf2xf5lfc":["auntieedna","Auntie Edna"],
"trqdmjmr6dx22fsr37kn7amr":["auntie","Auntie Kat "],
"ttxj2iide5lp53x43zuckfxk":["auntiecimex","Samosa Joan"],
"vutgsdyanussel5a53v2q4c6":["auntmarvel","Momma Pool"],
"xmkj6zlrluhtcgatvtfh4jgi":["auntubu","Aunt Ubu"],
"xmum25ztvju4ctshx4rkra6s":["auntjer","Aunt Jer"],
"zunpog46n7m7slrqh5cnm5qc":["auntkate","Aunt Kate"],
"lddzwszcpn2jvyb3fa54jifz":"auntiechocolate",
"tve6ibz2yjqcb5jxeadmeufm":["auntyjjc","auntyjjc🌸🎨"],
"3hnjtunziocqmhdaaq2kukue":["aunteerik","Rik, The Systems Fixer 🦹🏽"],
"7o4bgcgi4p2uxfpwz5m6a3hv":["aunder","April Underwood"],
"kmhdqup62kgcnlyj5wivfail":["aunali1","Aun-Ali Zaidi"],
"xtfelkt6zhubs4j46i3dgeaq":["auntiepho","Auntie Pho, MD"],
"seawqv4n3au6tx34hfwj7e6j":["aunnuhcodes","Anna"],
"vg4h5vh43izd7vz64zri44au":["aunysillyme","Auny H"],
"uegz6cnt74uwj2bx3lvydspj":["auntieknowsbest","Auntie Knows Best"],
"glrd7i5oxtyfdsckxc7mqhrf":"auntlily",
"qpd7kzdmofftbrtnet7pyxz5":["auntpiddy","Aunt Piddy"],
"wbnlmu5qflbq64saktidcjgv":"auntyippee",
"stcteg6g5tqjk7y7csqrbfmj":["auntiecarol","Carol Gardiner"],
"vufzcxxznotnc7cxanar5did":["aune","Aune"],
"h2cd57eghqyz4qlwy2hosv7y":["auntydemocrat","Auntie Democrat"],
"shuia6pzbvnkrgs5p4ygtw7s":["auntysophia","Aunty_Sophia 🇳🇬"],
"omtgeihgk6nyt5qjxweoklry":["aunjanue","🫶🏿"],
"obo3n3khrurg3sl4gh6gcw27":"auntiemama",
"pi3nvt5jvstmhz4svv4rgtge":["aunicorniapreta","Juh Almeida "],
"dqj25tpmua2j36xnzu23gsbg":["auntiehistamine","Auntie Histamine"],
"7plxikvtncjy76tze6akbdqp":["auntyinflammatory","this is your brain on drugs"],
"5wu7prarimqvyxcrwfaqpglu":["auntiegorgon","Queer Auntie Swamp Gorgon ✨️Adores✨️ You"],
"oby2afys47573bheifh2lrmc":["auntie-mommy-69","Becky"],
"kejr6p34dm3yoebn2f4frxiv":["feralfurbys","Auntie Roo"],
"qvvc66seg4hdbqwmtct2z3mq":["auntnancy","Nancy Steen"],
"srmfksyvp7aekgozchxornxb":"auntymiche",
"trdoj67xjc4jknuv7q7ocb4q":["auntacid","Aunt Acid"],
"xqkbtmcyvrpqclqeoliwt7pw":["auntfritzi","Shaindle"],
"5ld6bbdeufpxazq5edptrpi5":["auno","Ro Myr"],
"zilq6utogzzmgic6fp3hfugi":["auntiekee","crazy cat lady auntie kee"],
"h37fi7velttmfahnedgtg6nx":"aunel",
"se6qynpux2r5o5dun6rbs44q":["auntfeather","Heather"],
"4fxggr7dxsfnjikvahmlvz3o":["auntieplant","Rachel "],
"hpc4g3423fgfl6xyxyqriegv":["auntnanci","Aunt Nanci "],
"gyjbsjxj25uvbufrc7lnh44g":"auntylouie",
"um42sufedcgzfltor4ihryno":"auntlisa",
"lygryedxckffeaqqqo67zy2h":["auntdad","aunt dad"],
"6xwehh7dnxojvnjoyy7gz5uf":["auntmimi","Aunt Mimi"],
"ayqlut7uinwofzxco3on5p47":["auntiephoenix","Auntie Phoenix"],
"zitgmd4g2jlkjo6ez37jacw7":["auntiebacon","Megan Cahalan"],
"lfiagex26tzj6vfgockrfopk":["auntcunt","Aunt Cunt "],
"qqv3cc5n3rpr33iykhojfjvi":["auntiedarkness","Auntie Darkness"],
"hyntlmq7g4kzko4vnrg4bgne":"aunbaon",
"yjjwaqkd3ejlopvewzt4bwa5":"auntacacia",
"xmqdou3avl6ixtqix5gd3gox":"auntiej",
"shywlsmyvopkhrzrydhocofo":["aunion","aunion"],
"32s4awnp37xvkbu7kls7qhf6":"auntydolapo",
"ri3jxkycxce34dx7fl6cpssx":"aunterin",
"hzctnnamqirnuwqjpmq6kj5y":"auntkenny",
"nrb2x4syfubmssuepb3w4d3z":["auntgenna","Lady Genna Lannister Frey"],
"s7ool67rtgvykz43osloyqnr":["aungthaung","Aung Thaung"],
"4qad2vud75c4ttkv3wftsomb":["aunt","이모"],
"ef24xa63dc6blspphwigxi4i":["aunisien","Aunisien"],
"3lucan4mjwpev7mykvo37tae":"auntietherain",
"elk4yfj7l3huwa2w7mri2s6r":["aunumwolf42","Aunum🔜Wasabicon✨️"],
"la2ympexqqfbv6353q3pqi7c":["auntjettwillendorf","Witch Willendorf"],
"n54szyl7yr33qtlunfngr26c":["auntanawat","AunaunTanawat"],
"w366atafhn7yfukifjtiuaaq":["auntsmarching","nick"],
"gbjeo7xe25bsegu4dqq5usyn":"aunknorrie",
"2agyubgmoyk7m2i5zb5xr6ia":"aunoyp",
"hqjkx5lnazx4rqzecc6p3efu":["auntifa","Kimi"],
"rejtwhpz5phcc6nkgkcjsqqi":["auntcow","牛姨亨麗"],
"dglqcu2dtlvgdqzcniryhkq4":"aunna",
"nam5tbr2zrldrpijbtdmfro2":"aung",
"dodp7v6gwiqfmq72txefilhs":["auntiematter","Mat Defiler "],
"upvpexra2bpgcy5374x42fua":["auntmarilee","Marilee"],
"4aw22xb47cevshvf76tmrwtr":["auntyuncle64","Auntyuncle64"],
"i5rsa6o3nwb4ry6mo4ymm3lx":["auni","Auni "],
"zundvatrxgpapa2tpgyrfzxu":["aungworld","Àuñg Wõrld"],
"b7skbj3nph6igu7ybyd6ukqe":["auntyhoha","Danae"],
"bdgjdd7vj4fk5x6dsxlx7e7l":"auntiebrookie",
"jfbyxa3dlws34nsks5nvfbhv":["auntiewarhol","Auntie Warhol"],
"pubbdcugwx4m4kqfb3k3wqe6":"aundyrr6",
"dwkii63wljxyev7a4ovksj3p":["auntpolly","Polly Hala"],
"sm2di42a2ka6zgc7k3tk6opp":"aungkoko",
"quo4i6crsp6gvwepvg7filxv":["aunderp1","Aunder"],
"krmaxoudyaboi5jefc5vzfmy":"auntb",
"jjeyxmbs3ois4eb65b6zpm3k":"auntiecolleen",
"bkikj4h7obox2zcgzg7spwmv":"auntkelly",
"j5hib2ethqbjcpsiuscpv3bt":["auntiehairka","Busy Beav 🦫"],
"qp633dkcixbtaofcumilk45p":"aunnu74",
"5j3276xqb7iuclep64yq6v55":["auntgobbo","Aunt Bunnie 💚│Goblin Vtuber"],
"j7qchtkjtqzdmp6nhep5u7oe":"aunicorn",
"kdw55qz7wsbfsracuvmhosvh":["auni0","A. 0ni Dowser_digital"],
"uz4ogtx73wlcrumlepimrnqw":["auntiefae","Auntie Fae, B.A."],
"eskapy4nej7rgrmjvi62ewfe":"auntiekathe",
"osaj2pstbniuqfstqmpjn4a5":["aungkyawphyo","Aung Kyaw Phyo"],
"aj6u7oib6pu2h3iqdq7t4vam":["auntsusie","Rubylicious"],
"a4m5trno2bn7cthowkcal6o4":["auntycis","Aunty Cis"],
"at5bbnpi2sygoonrx2ce7b25":["aunjuli","Aun-Juli"],
"og3npjsas5psp72vazrknzt2":"auntannmarie",
"mj75de5isovxsk7ijf7tul67":"aundrea",
"gpqkgj6dd377bjfvjlorgrv4":"aunderhill",
"5iogqsmqjk4dshmoowljhisi":["auntiefiona","~Fiona~"],
"feoofkbiaenqbp5lxkvywuoc":["aungnaingsoeans","Aung Naing Soe"],
"wyeqdfbpaxcqprujovb75fxb":["auntiejoanne","Joanne P"],
"inkp456gioobwepixu7zhzxs":["auntyfox","Aunty Fox"],
"j3smlannu3zqb4zycejshyin":["auntiepegg","Auntie Pegg"],
"dztaf3kihleca24fihce6iw3":["auntylily","Lily"],
"velnv5n5tfd3t43wr66ca6jg":"auntdaddy",
"2qrli6cp75qgmyo7pimksayq":"auntiepasto",
"candjsngcmvqnuiy54yoaeab":"auntiek",
"7fgdzuuwwr3h6x7gdkn3ttmo":"auntiebooks",
"cvdxa7zy74g3xpgnmxmljmed":["auntkass","Kass Bestor"],
"q54xfxdewgyzpvxwetoclrpt":["auntsan","Aunt San"],
"7qamnwppdoonvapg5rneifhd":"auntlynnie",
"wmfwbq7paixeffuo4sgmvw2g":["auntiestuds","Kate Charlesworth"],
"52bp46vhlxjer4ovs77eircq":["auntiewsrr","Auntie ☕️"],
"i2lusj2v7uevlc6l5uqkbmgk":"aundyrr3",
"3ooi5mwl4c3wz6irz535fsgn":"auntsuesue",
"n2v44qzoff5g3vujmaomojwi":["auntieg","Auntie G"],
"7qf2b4or6azjggldbuznf7j4":["aungnainghtun","ANH"],
"47m2o33f2vhhau5njbiv3ymn":["aunty","Aunty"],
"ffoqnj4lqdjwm6y5hzkjdb47":["auntmeme","auntmeme"],
"3pukklllhmlhf3qp2hwkqpym":["auntieash","Ash"],
"sz54ood4yaz76dcsgg6e4n4v":["auntiekitty","Auntie Kitty  🫖 Vtuber "],
"n3vqb3bflzsaggumbnnkisv6":["auntiekell","auntie kell"],
"gnzqr5ag3fbp5dwgzfyahxk6":["auntiejess","Jessica Lubbers"],
"iuy5mvtbdje3yxpyq54xvaiz":["aunara","Aunara / Kitsumi / Sinory"],
"wwvk7uwouck3xabczue6hisg":"auntyfah",
"c5u2wmzhwigiqctxu3mnycza":"aundrelarrow",
"vzlkku2ns4vb7e34eoh7zg7n":"aundertheb",
"ebjpmsbninopexfadq7zn7o3":["auntieerin","Erin"],
"h3kvibt5umdg3blvg5tyiioa":["auntpix","Marifran "],
"7lcnfp2myzigcl3nzqt3hyqe":["auntiealias","Auntie Alias"],
"npp6yz7blzioua3zbbpzyrtx":["auniverseaway","raph"],
"jyuy5s4eb6mtx7dtvel3yidu":["aunderscorek","a UNDERSCORE k"],
"2rmrkdher2sazzcbsb6qujdi":["auntietelly","Auntie Telly 🌼🌷🌻"],
"pnyxiogvq5dewjth7jgsz5lh":["auntiemega","Auntie Omega"],
"hyqbpkkhzneuzmaw6ntvr2zt":["aunnobeats","gatinho cima baixo"],
"v3csuuwvrrzpyqjpt73x6cfl":["auntlucy","Lucy "],
"hsct6f6rbz6o6oluaaridv5m":["auntiealiasing","Fast Cars That Actually Make Delicious Meals"],
"ynthplbd5azsu4ihkviyuq6n":["auntieactivist","Brandy Butler"],
"rlgkwjqgg5yirjrzltnpxlvx":["auntygrumpycow","Aunty Grumpycow "],
"qdygmdpum2jqwttah5lgfmj4":["aundw","A&W Blog"],
"4svxqoihv3aucz2s74cgfq64":"auntbeth",
"fl4sgpsb3d76eqyapuvcm6uy":["auntcricket","Aunt Cricket(Macey)"],
"mtpb6liraf6h2u3uiwsehhpr":"auntbelle",
"sgwzmy5db3hoj2ib46mfgy6y":["aunkelbach","Andreas Unkelbach"],
"nsp4tchhik433u4ay5igouy2":["auntysocialworld","Aunty Social World"],
"qtwrbowr5oxyzotyq6ane7gs":"auntie-canasta",
"7jhdfjqzlowgm4cpmupxyir5":["auntiesebrina","Jen/Pepper/AuntSeb"],
"34zy6miqpvlssx7mmny6o7gg":"auntsophie",
"6o2ew6u3n2uqyqgotkgn4yrc":["aunbeats","Void meets the Galaxy "],
"tt6omusg2mbq36iemougi5dw":["auntiealex","Alex ✨"],
"sagwzqwh2fdsvlsyeo62dld2":["aun1q","Aun1q"],
"a35nz6ubpmbmnwdnhhext6h7":["auntdahlia","Jane H"],
"2myhywm5gusq3rzsvv4snm4r":["aunova.net","Aunova"],
"hstzqa5hpoeukvcoqmpm26r4":"auntadelepicard",
"g7uc4trpf2q6lzp75s67l3sq":"auntieniko",
"drvbjzhfo2atybjhhjmijrjq":["auntybob","AuntyBob"],
"mqdxpldjnooccu7a34idyunf":"aunthoolia",
"gsavxfssncwju2mmllyoxx4j":["auntiesusiebunny","Auntie Susie Bunny "],
"tuesr3eb4vyzkbqd3oacjlal":["auntieandi","Andrea S."],
"dr7fv7uvmc2jbx5qxxxqfooc":["aunioavem","Aunio Avem"],
"7eitghz255bkvdd5oifhne3y":"auntiespider",
"gbee7567hs7tcqt3ijqkooyp":"aunanners",
"6ljxzqddy7phbxwbir3pit35":["auntjolesch","Barbara "],
"b7jpr3ysowlaeifvnho4q7eg":["auntyshanti","Ashanti Whalen"],
"hflbyxdnwnucxm25hayo6ffa":["aunportraducir","Celia Martínez Duro"],
"6n7om5dlw2qor32edx4tfxt2":["aunteepearl","Councilman Yackson"],
"vlmr6g2ofi3jfzaijijreizr":["auntysiobhan","The Padre"],
"oqmrk73cjfjhtafmkdhqceuh":["auntbunny","AuntBunny"],
"xsskhglp26x2wjlqsuaxzyax":["auntieshoque","AuntieShoque"],
"zf7ikvlituqwo7dguhvl6dmh":"auntietiffa",
"jwqnn6cwmlj5d7572j4uar54":["auntieawesome","Awesome "],
"j67vqrrcoybohnpsfsao5vdd":["auntiejean1","Auntie Jean "],
"bumzsf2yfzbggs6lippxnjks":["auntieqrow","Qrow Branwen"],
"3bkkdosycqemv6jdurogiyn6":["auntygrimm","AuntyGrimm"],
"k2bff4amzntgkksbct3anmoq":["auntiewrites","Auntie"],
"4cbxkoetu4ip7hic7hquxtol":"auntbg15",
"pvtzk6g2gourcguejcomtogx":["auntiesyzygy","Auntie Syzygy"],
"duaoztvlmtrbeexnybnpxmk5":["auntiem","Lisa Deutsch Harrigan "],
"lh3kycaagayvzbjzyjzfq6v6":["auntiekristy","Auntie Kristy"],
"c7hqrhhn2wndytm7agnoccw2":["auntieze","Ze"],
"oh54vwa4b3wiwue4fe5hgpux":["auntieandie","auntie andie"],
"donc2ycjtx5dgplfapvyultx":["auntytang","Aunty Tang"],
"mjuqldazmawbrbbe7hprz2bl":"auner",
"b5zo54vxinqbzflwv7k5mhhz":["auntievirgo","Auntie Virgo"],
"ndkmdnbrznujo3poifsdggs4":["aungthuhein","Aungthuhein"],
"eoglgzqkqhu6yeyt3bawtynx":["aunaterrell","Terrell Manson"],
"wahq3tbedmiop3rldcfkbjs7":"auntcitrouille",
"fn7rmilibgz5yzoaraz55hu3":["auntnan","Nancy Huett"],
"chv2d5ydlcfrbeekipxtdpjv":["auntiep","Paula Bailey"],
"qme6c2ccacrq7daazfyg3qnm":["aunt-an","Тітка Настя"],
"zbwu4lzi4d3k243cjnwntstz":["auniformdrone","AUniformDrone"],
"ltfp2kplrtyadf7ikpeg4ot6":["auntiecody","auntie cody 🧡"],
"jmktatlelwcb5nhb5j6gpqb3":"auntyheaven",
"nbbadjj35o6vpi67patdh3yl":["aungpaoz","นุ้งเปา ツ"],
"eorwr2twyqu3qperhvg4vmd7":["aun-lex","Aun-Lex"],
"itzurwkfkn7b6edjxiwjhksy":["auntieheart","Auntie ☕"],
"ru654pq7k547xkuurrewlnho":["auntienene","auntienene"],
"2f66fylxbh7oak42parj2ws7":["aunazifi","AU NAZIFI "],
"ob374efq6a2mmnozxqk2h5h4":["aviationqueen","Aunt Benét "],
"3hc5zolhyfws6bv2wdorq5nt":["badbunch","Aunt Mange"],
"4cxttqd6tfzzbrwvlbdojcw3":["beaaeri","your local elderly aunt"],
"ycqqg4x33bfwcbjsezkta7yr":["bellelorage","Auntie Belle "],
"5v4wzrc2qvqztv67wmxn4qrd":["bibliodraco","Aunt Hedgebeast"],
"ttrc4zufceilsbuna4442kj6":["blastriot","Auntie Claudette"],
"qidu57wanwjhcni527zymbok":["bumbumslol","auntie"],
"jauglxa5vcvseqxwe22pljml":["carrotfiles","Auntie Claire & Angel Splodge"],
"3tolws2fw2hwuveikvgb7cbj":["cheeaun.com","Chee Aun 🤔"],
"r4avp3ftwt2qf55p4xqknt3c":["cherrypopstar","cherry popstar: battle auntie"],
"ao4wixwibclzrabx2osxgfec":["chronicmom","Petty Auntie Faw"],
"cr2vpclesjyicy3u27xj5jiq":["chaseaunspach","Chase Aunspach"],
"76huzvxmldmadwduanq7ccw3":["churble","Cheryl (not your aunt)"],
"urnazz6a3xtpwmto6xt23v62":["circuitbird","Fairy Donkmother (Aunt Birdy)"],
"df7xqfgyc2fyte5mldwkp6nr":["clementaunis","Clément Aunis-Oumghar"],
"mv5px644ilh5j2gokelrwxjc":["cmrhoffman","Aunt Christmas"],
"6sd3d5op6aen3im5bivgeawz":["cupcakegoth","Goth Auntie"],
"hk5guokxoy3ngjdau6g5upnz":["dahlingzoe","Your transbian aunt Zoë 🏳️‍⚧️⚧️"],
"tvgps2xrbsz4s5nett7yhkff":["davidqbyrne","Aunt Baby"],
"4kyvppu5pdfa2b365njyh6in":["daniquietnow","Aunt Dani (she/they)"],
"7ebieb72hbq3oqfdq5tyi54l":["deerteeth","aunt honeybee 🌿✨"],
"tmsr6v2u746axguvjdswlfag":["derekisnormal","Auntie Derek"],
"tqgnyvdds7vxvv2qp4c6cbho":["deejaydee","Dark Brandon's Auntie Fa 💙"],
"56hjbzdisz4kivgbczd5ckie":["diarmid","Diarmid / Aunty Bug"],
"655llrytilga7jouozryoztt":["dizzyist","cigarette auntie"],
"avwhl3hzx7la6n2eau36zlkg":["dollssoulkirie","Aunna"],
"cnlctf6ibujoecmtmzd6cdcj":["drunkaunt","Drunk Auntie Ash"],
"422ap3zckiixvyc7bcckbzuk":["eaunina","Elizabete Aunina"],
"yb6ksuq4vtzquymf3aay2j2z":["ekristinanderson","E. Kristin Anderson // Your Weird Aunt"],
"eqzikr3vk6avlbikmraz45un":["emaych","aunty kak maniere, vuil plak en dom krag"],
"lymdv3pb7vopv5q3jtqbbicw":["enlightenedauntie","🔮Enlightened Auntie🔮"],
"tbhojycjaybo74f62wlvujk5":["foxynick24","Aunt Nick"],
"7keffkb2uisdkjyacfujtar7":["frogirl","Auntie Babygirl ✨"],
"vraagex6ymrlw4w6fqqo6lq3":["gangykong","aunty marge"],
"xb72utbptv6sf2edfl6db4te":["glamgeekgirl","Ally Auner"],
"rhxsr2rq3dabhhjnaxqlbujl":["gooseagonyaunt","Agony Aunt Goose"],
"eve22ghvb24z7kdexwdfo734":["greataunty1","Great Aunty"],
"4olina2qzke2h2fxd555jje5":["hanskalla","Thomas Aune "],
"bclhohrhhb5gg6tgbxktnpog":["heathert","Heather T aka Auntie Psych"],
"iijrf2bj5afpw2se5xl55o2f":["hopeofasgard","Auntie Hope"],
"hgnsmp2kemmfru3o2jm6r3bu":["illuviel"," Auntie d'illuvian"],
"ajloacqa66pgahswt3uensww":["insanefoliage","Queer Auntie Trish"],
"w74azauqjrl45lhuytdicwos":["itsnerdybimbo","AuntiBimbo"],
"og2gy74dlfhh7duprkrkwdzg":["ivaraune","Ivar Aune"],
"b6x6g7am54kimdyzpenv2m4j":["jacklikesfilms","Jack likes horror films 👻#JoinAUnion"],
"pkzj4wltbmeim4nk6rpbdorf":["jayjaythebatplane","aunty jay jay!"],
"4vssylbmu3ikbeyhfsub77zb":["jillinmd","Great-AuntJill"],
"yxdzmr6hx6svqiero34fxa4t":["jilatlanun","85% nijicon 15% auntie"],
"xdt3ff46blfto4awp3y3mojt":["justinrupert","Aunt Jackie Daytona, regular human skeeter"],
"52s4orttorhzuhmjets7rpde":["katherinesmith","AUNTIE DOCTOR HORSE WITH BANGS"],
"g2wjmnua5plgitp3635agnju":["katebornstein","Auntie Kate"],
"lazg2rjjrf64f33f52kenlaq":["katauntienyc","Kat Auntie"],
"mhfr7zbb7tdrc7xu7qckgkgt":["kerthulhu75","Ray Aune"],
"esrmx7znyjqoulbvy2x4cxj2":["kiddocut","Doc Ock/Aunt May Ship Sailing Since 1964"],
"twcpkd6xqncqqphwsinsalfz":["kittykatya","Auntie Babs"],
"jkjcnq62iok6qepjworihjt7":["kitholliday","Auntie Fuuuuuuuhh..."],
"cacgvzqsrq4vkombrzyfwnz3":["kristenaundrea","Kristen Aundrea "],
"kupgfvzmbqjc5mwsrq7yjdw7":["kui","Dr Auntie Kui"],
"ii2lmbxfzlb6tupwyl3eubjb":["kuzzbuzz","Aunty Depressant"],
"hj3fhankycrkze4kv43dtufi":["kyitharaung","Kyi Thar Aung"],
"ebrsyd7vidxygu5tlgjngwvb":["laurenancona","auntie cistamine"],
"x4mpebedjkdyxnkdj3efwjfy":["lesliemuse","Leslie, the Collab Auntie"],
"qsd7fwlu22jwobkr5htbhd7d":["lilauntie","Auntie "],
"znv5bce44uivktp4fipmnxws":["lupulus","Aunty Em"],
"puem7sc43syvb24q34tc76i5":["mattaunay","Matthieu Aunay"],
"jtit46zjtckgown45wriyxmh":["meechietaughtme","Your Favorite Auntie 🤭"],
"ewn56punnqf3zrlvhojrmnlw":["megatorr88","Vicki // MegaTorr // Heathen Aunt"],
"gyurbwmlx7ioerig54wjvgsh":["mikeisbored","Aunt Ethel on the Scene"],
"hwyp4po3firn5hg5ctlixqwt":["moodkandi","Auncle Bee"],
"tpurbfhor475d5rxae2hn5rv":["mumakurau","that hrothgar auntie"],
"23oxviii4hnvpoh5xqwyzj45":["mumblequeer","Auntie Em"],
"iavb5plqrdvubbpluwtnclto":["myauntfanny","My Aunt Fanny"],
"hablomnfeopc4xhz37k6hbok":["nanovyne","Angel/Aunix"],
"g2j2q2rwqxgb3vsdfipknmhn":["neko3","AUN"],
"kprr32xvv7x7qfhduhjel2iy":["notelling","Aunt Rose Comfort"],
"gzjxh5w3estjdpuyuacbj327":["nugs","Auntie Nugs"],
"h37dtqwhgdnhhyj67mp3tete":["ohmygiddyaunt","Oh my giddy aunt"],
"iax2lts342tj3sz3o6jvut5v":["ottawanag","Natasha Gauthier, Destiny's Auntie"],
"tiw6cbgvw7jjkgilkxrfbvlz":["pinkcolorpen","(Aunt) Pink"],
"ymmfdfq6oikfnjhllkczedfn":["pongi.no","Simen Aune"],
"6toja46phcogsh6mnqmerfbp":["puruniy","auniy"],
"w2ehrdustmsqvdcp3pymtmlx":["queerauntie","Auntie Collins"],
"jvglkfpxbltqymx7dkievxmp":["queerwitchauntie","Queer💋Witch🖕Auntie💃"],
"wdhhek44aiq3mh2qampuzube":["quirkyne","🌷Aunalicia🌷@comms open!"],
"pdcqsbjyoqbbuhp64bt5ic5j":["raneaunimo","Rane Aunimo"],
"zhqabmcohtnflitqqwf26ifm":["rarrahrar","Aunt Aoife"],
"w4wkmh2bcn3iygwypttp3jwx":["refyll","Refyll: Auntie of Light"],
"f3taajnjyts34dmwxmnumsfz":["riversdaughter","Melissa \"Auntie Yaga\" Carr"],
"d6p7hoj5mlhxmvewxgjiwbqw":["rowzdower","Auntie Oedipus 🌱🏳️‍⚧️🏴"],
"jasnuxsyojrmrpgqy5qv32y2":["saveelati","ᏣᎳᎩ Auntie & Grandmother 🌾"],
"vf5ppghy5nkjhaupzyiuvvtf":["sakkhor","Aunnur Sakkhor"],
"ksgn64lactqmev6cau4aftg4":["sassyauntiek","Auntie K. "],
"fpwmzerokebjm4win22zl7da":["seanpaune","Sean P. Aune"],
"em62gorlnu5sbz4y3wcbdb6i":["sentrydad","Chris Aune"],
"t743aokmoyr6c5tgplcvuefh":["seirai","seirai ❀ astolfo’s aunt"],
"pfhs5vtupm4rjb4wdrywe6of":["silentsyren","Bog Witch Auntie"],
"yhygciudbc4kzcjki2una22s":["singlelatency","Auno"],
"ju3ibp66hiw5ot4u4uc3apde":["songkran","aung"],
"2vvxav3cw26zecyzeq63grmq":["soonilina","auntie lina "],
"4i7h7cvnd6iekb6q25snbbgn":["spinster-auntie","J_Lynn"],
"afj3o7yatzf64x5gekjalbad":["srslymagenta","Your Weird Internet Auntie"],
"45dmumrmyehdynrsbbqywqgj":["strangie-auntie","Strangie 🙋‍♀️"],
"afderfqced3bkr4qzu7mjmez":["starlightriver","auniqe"],
"4kw3agoxeq3c6galqxyscjve":["tanandra","Auntie Tan 🏳️‍⚧️​🏳️‍🌈​"],
"s7icsnwbpz5vkxqzdx6dazlm":["tantefledermaus","Aunt Bat"],
"euxddt2ex5nfdrw3fcnub4hd":["tarawiel","Tara | Your cozy internet wine auntie."],
"wfxladucmpkgdsokevuh3tou":["terrythescary","auntie christ"],
"cf56k2z3f6nez7esfrt4xte4":["tedde","Aunt Ted"],
"y33ydht6sf5qh5evaferv3cg":["teoweg","Auntie Social"],
"4tmz662nuqkfgsfwsfpqxt7k":["techcryptid","auntie depressants"],
"yqioo5mcwkzherlbq7dykcr3":["teamburma","Chris Aung-Thwin"],
"skexgswshgptn3isquqzjk6g":["thatauntzelda","ThatAuntZelda"],
"fobhphmvmwzx2ytasfx3xcu5":["thatazurefluff","Auntie Charlene"],
"3ovgmukq253mjgvwwdk3qlwy":["therapygames42","Aunty Mel"],
"4dnxkxfj2dqvwcj27t5dtbek":["theaunties","The Aunties"],
"i43lipagx4a7fg6box5dgkzb":["tiaglad","Little My’s aunt"],
"v3cpwjtx6ia5kp5actiddjm3":["tiorwenmaz","🔞local wine aunt"],
"r34w65wkqjsxvzbp5fg6wxa5":["tofuhorse","auntie dipshit🆒"],
"zays26wj3x3qhshrs57jyfcp":["tommytimp","Elon's Sainted Aunt"],
"quskqtfcjzspo2hnflhz6v4g":["trixietricoter","Auntie Deb"],
"3k2uozohtt4xacwxrsjku5jn":["tracymalikongwa","Aunty_Mufasa"],
"4pbh734zuikflahjsytzux5r":["transbianauntie","Your Favorite Transbian Auntie"],
"ecfovkydxgb66cc2q6suhex2":["tyrelvin","Aunt T"],
"hwdbihaypkj3ifa2dxgqd7jj":["undeadauna","Undead Auna"],
"2nkwjr64ve47lzps5eludjpv":["vashtib","Aunty Vash"],
"twvvarnpgtmhnaqypssln4wy":["veronikakestrel","Veronika \"Auntie V\" Kestrel"],
"wlszr73pcoqtspw6l74dm5j7":["virtuaplatinum","Auntie Christie"],
"z37eyn3srgcr6h2nmrj46l7s":["vivekaclaire","Auntie Viv"],
"zs6tvzedk7mhz6rfu6szr7ix":["violetfeline","Auntie Lisa"],
"myoqccdm6kaekgegcarl7fji":["vicieree","Vicie Ree aka Auntie_Social"],
"xzyw3syfrobmr3w7tp4r6utt":["vjcagle76","AuntieVj"],
"weeqwviays443jpbhfynbmbp":["vodkaaunt","Vodka Aunt"],
"ykbw4atp3a53sqr4cwwkjgak":["yami0204","❄Auntie Erin❄️ @ 🐴💎 brainrot"],
"su5biwjavxoa2wlidki4zd7h":["yourauntie","YourAuntie"],
"yh4r7kbivd434rbxz66fqxxh":["yrauntielola","xiu xiu vs steely dan auntie "],
"f3e37fzj4cllrapwunihexqe":["zeroiqrequiem","Aunt Jemima"],
"hr3gyfvms4qpjp76risxm5xo":["zoiid","✨️Princess Aunt✨️"],
"dmnkpv2pmo6dmwjq7z564uyu":["aunaun","예"]
}
