{
"ojmsb5pc4o6tvlzxrhy6dqjy":"9atnight",
"kzyyvlpnefstd6qnwwndreqq":["abstractlite.atnms.zone","boy dyke⚧️"],
"snerkrlrwtv3lcpnfxaven3e":["atnicki","nic"],
"iolkgps4fpjpypzltmdi7hkp":["atneduardo","atn"],
"arrj3tyqzgwflykwxjzcmaxo":["atnathanyaffe","Nathan Yaffe"],
"gddaoenmaxg4t5hzzanxk2p3":["atnbueno","Antonio Bueno"],
"cqzx6pthw3tcco6zrnb6uuxm":["atnight","밤"],
"ovmwexnhddgeqkd5ppvliyz6":["atnithecat","앳니"],
"fc5chktznuvfczcsovv7cbpi":"atnanahidiw",
"mv4y7v2ns3hskt4spyqavbtt":"atnicksand",
"kmnijv4r47ev6f4jp7vtgh2i":["atnafb","Atnaf Brhane "],
"sbi7r4qiprq74k677gh7deqc":["atnpgo","ATNPGO"],
"qgirl6plnjwnq6phdlfgpyvf":["atnorthrup","Throatwobbler Mangrove"],
"pq2xzmnaydm6l5ejppgezxcd":["atn","M"],
"bbyzroywuthx5fqwrqx4wfbn":"atnguyen",
"lpve6xh63t2d26bhx23hxaab":"atnyc",
"aouvyx2xtvvufkaheo7cchja":["atnepal","Giuseppe"],
"efz2rcqny74pkk4gzigmmfe5":"atnic",
"bm667xx5l2z6a7hi45qfyequ":"atnajoy",
"w7trcdymlbce2qxiqa7tafpn":["atnak","Ats Nakamura"],
"wdv346hptozlfzqwqg2pnybb":"atnmn",
"xsts7se3wo5l7mur22xnqhuz":"atnatsu",
"2riwm6p6b4fvwmaxulcarxed":["atninokawa","Aaron Ninokawa"],
"hchs5jvyxvalg73pn5ajmsev":["atnasama","Atna"],
"muney5ig3pergpo2rqgucaw2":["atng","ATNG"],
"eas5fayg6ixqkortgqxz36gv":"atnfootstool",
"qnptytbpcxazo7kmrrbs37aq":["atndris122","Adrian122"],
"wqbrh5sz7ge4nypc7b7rajje":["atndbs","Antonin Dubois"],
"dy2h74rx3pc5ujhy3ojhnowt":"atnsfwa",
"m6xhzup2izuccqnne6gyklfx":["atnafram","Maryna Chuyeshkova"],
"y75yzzxrf3xql3mtwk7bqxdy":"atnl",
"ppkoecxwdvdj2d2zsuxbqpus":["inkeduprunner.omg.lol","Jason Atnip "],
"wqhvabhucki5ux2bm4c4f52u":"lastgrrrl.atnms.zone",
"hjmgbvpsk4wdryihsbnrnayc":["rl1atn","동규"],
"6wkzxu6idkp4wgwjn5dqpzra":["sylandi","Lin Atnip"],
"fwj2x35gyeqwbif5o2vgjtko":["teagarden","Ma'atnofret // TeaGarden"]
}
