{
"ln6sfuxrzoax7h57drxrmsj2":"aashirsnani",
"uesfqxo2dt4hsz7faw6jpvzb":["aasiegel","Alexandra Siegel"],
"vi3iiqcqqajhdsgjuoxosfly":["aasawj","Åsa ✌🏼️"],
"ke5pshjjggqfqo2fpg65b36p":"aashiq",
"ybsdgtkuxa3br7jlv7zim5jg":"aas",
"hqxmyr5revswnouwnn2djrvs":"aashka",
"vkexjxpdwiqxqo2n2mky5kgy":["aasimah","aasimah"],
"uwxanxtwmt3sw4dv7hgrjfiy":["aashish","Aashish"],
"a5tdprbtx27ho324slgtqktw":["aashif","aashif"],
"tz3klkbaqhg4m7ui2cr6bgef":["aasma","Asma M Salamat"],
"hboyw5on5pop4stdmd6s3w2z":["aashutosh","Aashutosh"],
"btdgb4xy7itlfvia3ghqcow6":"aasun",
"piojnsb4lvcibisdut7iwpa4":["aaysha","AASHU! "],
"ozvsp4vrk5avfbdec2ouoi3n":["aasimon","André Simon "],
"xcpp5p4azlsf7y2jf7rxmaqb":["aasta","Aasta"],
"k4avszjcyduqgix242n4pyje":["aask","Aask at the NFO (DEFCON 31 HERE I COME) "],
"k3i4sel3tzlpnyys4eg6msmw":["aasterisms","Aster 🌟🌸🍒"],
"fkf3zwyl5vkiyuv5pdyhwyxe":"aashishbyni",
"c35reontpegyxpmk2qjpogyy":["aasemaan","Aseman"],
"ojmys3cw5mkt4gcbjh5lechs":["aashna","aashna🫡"],
"zg3s4azpynoaebxpli4bf5ta":["aashishc","Ace Capital"],
"fbj2y4urh5n2jv6bwytnfwfi":["aashkadave","Aashka Dave"],
"ijr2qjrbdbi3hlelvthbefwb":["aasmashaukatmd","Aasma Shukat MD MPH"],
"g22ysdoc7xwlepdpc53comyi":"aashaw5",
"2f7nqtkmwrbir5epgvjot6fr":"aashay",
"whogisx3cvfqercidsjl5geh":"aasheeshverma",
"3f6bgny7gtlcuwu3uu2cumg2":["aasmakov","Andrew Asmakov"],
"ur3xvqh4nn2ofm6g2yotlovh":"aasaarrr",
"unprnkutsgaz7is5hu44zgc3":["aastrobee","Astroobee"],
"c67cawpqsr6kjxbc67itth7z":["aasaman","Aasaman"],
"qeztz35dvtm3mmw3shfvfslu":["aassdd","asd"],
"6hpcsj4khbhjdl5muvdn24h4":["aasehanim","Ayse Ulker Saygan Solmaz"],
"mt7m33ddw7a7h7ir4vb6l6mt":"aashisho",
"d53qi7zpki7p745qy4aj46ih":["aashishd","Aashish Damani"],
"4i7d3vycq454pdnz757jbv5w":"aasif",
"2xurthemye55c5d5y3okao33":"aasmiee",
"dztbvfa2w5uixidqxoay7nir":["aascensao","André Ascensão"],
"dzqnwtwv47cirsxcmjapjk77":"aasodamola",
"defhiojdau3m5bvrly2taxji":["aashisjoshi","Aashis Joshi आशिष जोशी"],
"j6akhfkuwo6f7ydzoc72drws":["aashisham","Ashish"],
"nn4jgk5nzxuz2xznyli5tr7c":["aastronaut","AAstronaut"],
"eqsch7hrkm5r3czu5oey6knx":["aasenjo","Alberto A.D."],
"u6ilgmdpqr4hyivzttgkhjsd":"aashnakumar",
"zxn3gnhiiyvzidtj77yeh6nh":["aasthauprety","Aastha पास्ता"],
"pabli5q2knkc2wdc73hjawtn":["aassissouza","André S."],
"wjscf4ybix5guvtf4i2zd7bz":"aasmehren",
"bglakcuivf2n7pif7vbdbmve":"aashray",
"5gzjgsengasnczyftw3dwrlq":["aashtonwriter","AJ Ashton - Fantasy Romance Author "],
"c6arf32p5qkfwxjbn4xpa7xt":"aasiaat",
"pkmpqdu7ya5724sux7mlddfu":["aaswath","Aaswath Raman"],
"olhvqy3j66c5h2xxgdocum3m":["aaszerman","Adrien Aszerman"],
"kin2y3yy6rausqdl4rfgc7db":["aashley","Mr. Ashley"],
"zufmz3vurk27votrp2ptp3pb":["aasnar","Aasnar"],
"zql3nmfhfvquvrcd4erpqqvg":["aasew","Åse Wetås "],
"ay37prjsgoitqoqeyqhihwou":["aashika","A.A SHIKA"],
"57olgpqfib2ytow7pbpyqwkw":["aasmagmojiz","aasma mojiz"],
"sikv3gm4b2nfrklbtfplc7gm":"aashacowey",
"izuxzykwe7c2fzlpcsix2ayw":["aastaneh","Amin"],
"6qf2ogot5uuqvpnk7767kk3z":"aasimar",
"pcplksw6e3inu5pbah5z52il":["aassfxxx","aaSSfxxx :þ"],
"iq4owi4vwdmtoohrlztfuhqo":["aasadd134","퍼런망아지 "],
"hrpcli7y46log5zpii5jttpg":"aashishreddy",
"ekgcujq3jboluc7yy3usn4le":["aasli","aasli"],
"upbjsrkm3y23tphx57qmlsns":["aasthagupta","Aastha Gupta"],
"coetzpcna2ca77meacikt7lm":["aasaxena","Aayush Saxena"],
"aqkrlojokidg4567ssfhbazv":"aasitter",
"c3x2nigpnwiahkcgnzi7poir":["aashishg","Aashish Gupta"],
"sy3px7oeauz6byglcuh2qg4j":["aasewell","Alyasah Ali Sewell"],
"6aio4m5jzyt74seubslo6pql":"aasmund",
"apdyc7elf3ljs6hwo36yzuz5":["aashleyb","Ash"],
"c6qztcy73zf625yjbzllei2g":["aasdada","Falso Pepe"],
"74yb23ajtzwkbttxpabsypqj":"aasshhlleeyy",
"tbizu6ngr7atwouib67f3hua":["aashirya","Kathi"],
"xlxrzchcmpbl44lfgwozrffc":["aasderbasis","aasderbasis"],
"ip2raln4rgitvehbgn5v4aaq":"aasis26",
"bbza7hufneze5kza6xl2tjpn":"aase",
"hytzx5peomphoqsvqqr6wye7":["aash","Aash 🦊"],
"b2djidhcb27jmstwgmrtnuzq":"aaston",
"4cfrypripfg2obacqulia2co":["aaso","아소🌱"],
"gvlnwmx5y7hhayy4flktlqaz":["aashleyy","Ashley"],
"eppkwdx6g4xobncmnwm33m32":"aaskuea",
"22e3wfaysx6bwwfpzybouoqu":["aasagumi","lea"],
"e2x6zme5s5xwgpbo53vdki5z":["aasttuamr","Astrid"],
"54l4tzixqjcguaqvbcvng62n":"aass",
"lugq3swos3l7ln4xraxwi7hn":["alexaasimar","AlexAasimar "],
"avbskhtledrqkpwbx377ewbh":["andreasaasheim","Andreas Thon Aasheim "],
"g6lk5wxzrkoh2kxntx4po7ww":["andreasaase","Andreas Aase"],
"hwqiu7s4wfbhh4vsxa5ojczx":["annetaran","Anne Aasback"],
"dz45nvqjcply2e4julc3cptd":"aria-aasi",
"nvui7vbvy67z3jsn3dbzmiai":["ashaolinmonkey","Aashish"],
"74nq4xbwdcnsow7kq6rpcpvr":["drchriswinter","W. Chris Winter, MD F-AASM, D-ABSM, D-ABPN"],
"e2s2bxs5z7xsfs2dk53rzxul":["egilaa","Egil Aase"],
"i7niivmy3yssdabmrm43cf6j":["farmlesbian.com","aase"],
"52pzg57uni3jpuac7sfwbqlr":["frankaaskov.dk","Frank Aaskov "],
"h7dykrntyfhidlczdyc4zosc":["grouch","Grouch|AAS"],
"7zo76h5fb5dbr2wb7vnblffj":"guy4aas",
"nxrpux4sg2mi6umourbieufu":["halvor","Halvor Aas"],
"wjz4dsesa3hemkcea3t66md6":["haakona","Haakon Aasprong"],
"ixzd6ln4lxgxzukg27l2nji3":["hegemoniet","Hege Larsson Aas"],
"2tvcxernh47nknmsm4jma6a5":["koblr.com","Guttorm Aase"],
"rincprsc365k362frf656awp":["kristianaas","Kristian Skjellum Aas"],
"2sasbcy7tgnwnrbvvdz2rcu7":["labanlars","Lars Aass Olsen "],
"5n4d2vozsnwna3rdkuxz5d53":["matthewa","Matthew Aasen"],
"o7ouu62tv4uo24ah3senlhto":["missingsheep","Aashim 🐑🧿"],
"63lgrag7axnzurqubapyomrg":["nrkesp1","Espen Aas"],
"nruo5nli677qc7d4m23fd25h":["oleaasheim","Ole Aasheim🇳🇴"],
"ybtyn5l4nljys46ijqtpldaw":["patigallardo","Patricia Aas 🐢🏳️‍🌈"],
"kb3a7eis2u73ulbuxfq3nddk":["rosgakori","Aasa T"],
"bzp3bct3behi3giu5c6vda43":["saasluver","lover of aass"],
"ntdkak733fedctx442jlexmk":["sjova","Åsne Midtbø Aas "],
"mglajltg3m443tdy2inqoitg":["stigaasheim","Stig Aasheim"],
"v66w3xzar7kst7jipzwiovgm":["stressedasia","aashia"],
"sbmka4ytbrhegwdeycy6kolv":["steinar65","Steinar Aas "],
"rwsp3xdymbbni3nzkbfpu23b":["vigleikm","Vigleik M. Aas"],
"ivu2e5bmacbev3565fzllixg":["vildeaaslid","Vilde Aaslid"],
"zqc6y4zi5c5cx6okpvhvzlh4":["wittleas","AAsia - ✨In purgatory w/ Bk ✨Rambling like Dk✨"],
"zswnheitrghxdfmh37qmobdz":["xcrookedxedgex","Dr Aastössig"]
}
