{
"btwajle24saryneg357okq5x":["actionschorle","Simon Apfl"],
"2ahzjogpitknbt4iu4kd6uul":["annapfel","anni apfel"],
"4ogtoqifujuzrfqeijy6vjsn":["anarkissed1312","defend the forest // stop cop city // investigate APF"],
"bewkxfr6uxbktot6cfhrgtiq":["andreas.apfelfreunde.de","Andreas Harder-Matern"],
"xyjalcvtl4ah2mbh6nvetuta":["anneapfel","Anne Apfel"],
"52v2cbd3ajm4easir6jl2lte":["apfelhimbeer","Apfelhimbeer "],
"cffh42nbtjbo6l72nmjjhdeu":["apfel078","io"],
"nhtfumnbdsumwbqd7ah2uutz":["apfelschorle157","앞펠숄레"],
"s5h446f5pacixofdpwjl4jqa":["apf","Adriana Porter Felt"],
"wq5773myudpbmmvtyrqwjruk":["apfelkernchen","Apfelkernchen"],
"fhohgeduothw3odxkdvxsuov":["apfeitosa","Ana Paula "],
"3a7bpezz3omgvrjodjtb3nz7":["apfelskai.art","Skai but BlueSkai"],
"fkpfkctlptsq3z7ahmzpiq55":"apfensk",
"g6saqpdutubzdxiyt54xx4zr":["apfeifthewife","Allyson Pfeifer"],
"n635zv45jfyd2ra5lygclt3n":["apfel08","ジギー"],
"ne4leg4ff6pzeuk76jajc5ug":["apfelmann","Chris"],
"h7s6ff7hmudsw2lwgex6gp5s":["apfelcider","금사과"],
"4od4fy4qus2kiokdautkniff":"apfelos",
"nfiwyafgc2s6qaek5u3ao7qm":"apfelkuechle",
"ooqyf25k6nfgwa336uo7ncqu":"apfs83",
"skaqbgle3js7c4fpefpn7c5n":"apfulton",
"ioaggca7yvr5ct45i7hs6cu6":"apffh1",
"5zmlfey5zybmmngmir5d5ypi":["apfel","아세/앤시"],
"v3bqmx2lahbb4ozobm2rk4j2":"apfou",
"cq7vdf7bza5yfvksthnqrodk":"apfarias",
"frtxyzcjcu7sdf3dwy522kkn":["apfelwolf","Alpha_Ki / Apfelwolf"],
"2y7yj4jdhqmryuqf2zeytxzi":["apfelauto","Apfelauto"],
"6yh4do5yzv2hoslufk5ahocu":["apfokat","Der Apfokat"],
"iajabcw6t2ts6766ntd2qvte":"apfelsine",
"nm4y2xq3fjgfsf77s7iojbmp":"apf4",
"mri2cuc43jflcgjrx3sq7gzz":["apfam","Angela Pfammatter PhD"],
"agyexohdwsujjmikxilaukoy":"apfelstrudelig",
"fxv7tottqqwwrhe3vdxbgyyw":"apfelfrisch",
"4wwo6uwcjeunocvztsicik2i":["apfelsaft","Sebastian Frik"],
"462uegvrp5ruwzws67f3xk75":["apfelfunk","Apfelfunk Podcast"],
"a4jn4kpnwlaiejy5in4z2bkl":"apfelbaum",
"2xgkjw4dnw4i6wl27ewcz4fk":"apfelsinia",
"npp7onipk4gjavaij3jcfmei":"apfelbokel",
"afurjktdr3egfiq46wqkious":"apfelschorlenbande",
"mkchrrqvadnpsxb7vum7sq22":["apfsuna","apfsuna"],
"3afc7djryj6mnooahdrffnsy":["apfelkuchenkuh","Mayotee"],
"2kvyh7b6rjqwuaaho4rdzlhy":"apfelmus",
"6pt534245x44xhp6x7orrxlb":"apfellus",
"45zo3dlnvsfvxuqjjtzwkxz4":"apfelkraut",
"tx2xklyvmsnygx4e4gpgif33":["apforz","Adrian"],
"rid4hups7daky7axdylnhj4e":["apfelkern11366","Waldfee"],
"3l43big72py4pydsrigl4vsk":"apfelbla",
"4vmn3gzu2qeyfajjclau5sde":"apfelstrudel",
"rxesc3b32skkwy4lt2bwabq2":"apfelk3sekuchen",
"v3kbogg2kaujjwklwb7rutxr":["apfzu","朱阿水"],
"y4fye7cy7worx3p4tzhwngzr":"apfelbasti",
"qhou7gjnngdzdyrj7uhzyflm":"apfelbaeumchen",
"dvepybi2hvvszfgofeo22zae":"apfelmusmann",
"nt6hhsj2ip7bir5srdw4qok7":["apfeltalk","Apfeltalk "],
"67stsblr2spkgesjjksb7lb5":"apfelkuchenachim",
"cdi4cpdvv5cgamfarrtdxkkt":"apfp",
"556np3h44cul7nxb7dvuxu3o":["bratapfel","BratApfel"],
"goncna4fjzay3vkkmapblb3d":["halberapfel","Halber Apfel"],
"idy2ydbtpckgtatdebw4ciu7":["javierapfeld","Javier Apfeld "],
"yur2o5b6p3kmq3t246jd7f7w":["katgruen","Kathinka Apfelgrün 🍏"],
"elkam2xayi3v5v7dun2nnlp2":["lewd.apfelskai.art","LewdApples"],
"pgggyd2mxnagumyt2e3e7s4s":["mapfelthaler","Matthias Apfelthaler "],
"5wm6kijgpnkagevmeztct5ia":["petra.apfelfreunde.de","Petra Matern"],
"l67get2ajbtofqak6thuctkv":["pixieapfelbaum","Pixie Apfelbaum "],
"w7iav5feerqgbkefmvnrr4v5":["rukaapfel","RukaApfel"],
"jswimuzcfpxiibcbmwsavdt2":["sueapfe","Sue Apfelbaum"],
"ysq3xidctd4oi7v5h2zuprid":["sylviaapfelbaum","SylviaApfelbaum"],
"jnqjwnsp475tm2qisq22csw7":["tildaapfelkern","Tilda Apfelkern"],
"g36bckkukmyeeqpqe2uv5omb":["weissdochauchnicht","Apfelkuchen"]
}
