{
"olhvqy3j66c5h2xxgdocum3m":["aaszerman","Adrien Aszerman"],
"g7l6rxlg6gejfywepy2jv46c":["aszabla","aszabla"],
"7ya74bfcvkyv6nlzam6kr7oi":["aszulinska","Agnieszka Szulińska"],
"pvvcwowwuetz5opqjaii6lx4":["aszto","aszto, funny animal person"],
"sgvva2rvm4vj55t53dhttefq":["aszheraffxiv","Aszhera Ngrit FFXIV"],
"rwckzkd422uroxmrhh4rzavd":"aszemanski",
"tu5tljqyd4xnaxsf6gty6ljj":["aszurvael","Aszurvael"],
"niqobxc4sip2wawotousakty":"aszenth",
"ssqje2zre5totgtfyhidu2xv":["joeyaszterbaum","Joey Aszterbaum"],
"3ofosl5zoahnifpzpsfhyvzi":["monkeyjuggledx","Andrzej Łaszcz"]
}
